gc_integrations/__init__.py
gc_integrations/config/__init__.py
gc_integrations/config/keys_config.py
gc_integrations/constants.py
gc_integrations/hltb/__init__.py
gc_integrations/hltb/client.py
gc_integrations/igdb/__init__.py
gc_integrations/igdb/client.py
gc_integrations/igdb/models/auth_models.py
gc_integrations/igdb/utils/__init__.py
gc_integrations/igdb/utils/utils.py
gc_integrations/utils/__init__.py
gc_integrations/utils/to_async.py
game_core_integrations-0.2.7.dist-info/WHEEL
game_core_integrations-0.2.7.dist-info/LICENSE
game_core_integrations-0.2.7.dist-info/METADATA
game_core_integrations-0.2.7.dist-info/RECORD
