Metadata-Version: 2.1
Name: game-core-integrations
Version: 0.2.7
Summary: The integrations library for GameCore.
License: GPL-3.0
Author: Lamarcke
Author-email: cassiolamarcksilvafreitas@gmail.com
Requires-Python: >=3.8,<4.0
Classifier: License :: OSI Approved :: GNU General Public License v3 (GPLv3)
Classifier: Programming Language :: Python :: 3
Classifier: Programming Language :: Python :: 3.8
Classifier: Programming Language :: Python :: 3.9
Classifier: Programming Language :: Python :: 3.10
Classifier: Programming Language :: Python :: 3.11
Requires-Dist: aiohttp (>=3.8.3,<4.0.0)
Requires-Dist: howlongtobeatpy (>=1.0.5,<2.0.0)
Requires-Dist: httpx (>=0.23.3,<0.24.0)
Requires-Dist: pydantic (>=1.10.3,<2.0.0)
Requires-Dist: python-dotenv (>=0.21.0,<0.22.0)
